django_register/__init__.py
django_register/base.py
django_register/rest_framework.py
tests/__init__.py
tests/apps.py
tests/models.py
tests/settings.py
tests/test_admin.py
tests/test_choices.py
tests/test_field.py
tests/test_register.py
tests/test_serializer.py
tests/migrations/0001_initial.py
tests/migrations/__init__.py
django_register_field-1.0.9.dist-info/LICENSE
django_register_field-1.0.9.dist-info/METADATA
django_register_field-1.0.9.dist-info/WHEEL
django_register_field-1.0.9.dist-info/top_level.txt
django_register_field-1.0.9.dist-info/RECORD
