Metadata-Version: 2.1
Name: django-register-field
Version: 1.0.9
Summary: A field that returns a python object.
Home-page: https://github.com/MaxDude132/django-register-field
Author: Maxime Toussaint
Author-email: m.toussaint@mail.com
License-File: LICENSE
Requires-Dist: django >=3.2.0
